rb_tree/__init__.py
rb_tree/main.py
rb_tree-0.0.6.dist-info/LICENSE
rb_tree-0.0.6.dist-info/METADATA
rb_tree-0.0.6.dist-info/WHEEL
rb_tree-0.0.6.dist-info/top_level.txt
rb_tree-0.0.6.dist-info/RECORD
